brawlPY/__init__.py
brawlPY/brawlPY.py
brawlPY_2024-0.0.2.dist-info/LICENCE
brawlPY_2024-0.0.2.dist-info/METADATA
brawlPY_2024-0.0.2.dist-info/WHEEL
brawlPY_2024-0.0.2.dist-info/top_level.txt
brawlPY_2024-0.0.2.dist-info/RECORD
