Metadata-Version: 2.1
Name: brawlPY-2024
Version: 0.0.2
Summary: Library for accessing data from Brawl Stars API
Home-page: https://github.com/gusejuice/brawlPY
Author: gusejuice
Keywords: python,API,Brawl Stars
Classifier: Development Status :: 3 - Alpha
Classifier: Intended Audience :: Developers
Classifier: Programming Language :: Python :: 3
Classifier: Operating System :: OS Independent
Requires-Python: >=3.6
License-File: LICENCE
Requires-Dist: requests
Requires-Dist: python-dotenv
